p4adev_tools/__init__.py
p4adev_tools/ftp_server.py
p4adev_tools/ipykernel_threaded.py
p4adev_tools-0.0.3.dist-info/LICENSE
p4adev_tools-0.0.3.dist-info/METADATA
p4adev_tools-0.0.3.dist-info/WHEEL
p4adev_tools-0.0.3.dist-info/RECORD
