Metadata-Version: 2.1
Name: p4adev_tools
Version: 0.0.3
Summary: Collection of widgets for the older kivymd 1.1.1 lib (material design 2).
License: Apache 2.0
Author: BlackCatDevel0per
Author-email: bcdev@mail.ru
Requires-Python: >=3.8.1,<4.0
Classifier: License :: Other/Proprietary License
Classifier: Programming Language :: Python :: 3
Classifier: Programming Language :: Python :: 3.9
Classifier: Programming Language :: Python :: 3.10
Classifier: Programming Language :: Python :: 3.11
Classifier: Programming Language :: Python :: 3.12
Requires-Dist: background-zmq-ipython (>=1.20220901.135250,<2.0.0)
Requires-Dist: ipykernel (>=6.29.4,<7.0.0)
Requires-Dist: ipython (==8.12.3)
Requires-Dist: jedi (==0.19.1)
Requires-Dist: plyer (>=2.1.0,<3.0.0)
Requires-Dist: pyftpdlib (>=1.5.9,<2.0.0)
Project-URL: Documentation, https://github.com/BlackCatDevel0per/p4adev_tools
Project-URL: Homepage, https://github.com/BlackCatDevel0per/p4adev_tools
Project-URL: Repository, https://github.com/BlackCatDevel0per/p4adev_tools
